fishpie/__init__.py
fishpie/database.py
fishpie/files.py
fishpie/i18n.py
fishpie/index.py
fishpie/login.py
fishpie/wordpress.py
fishpie/static/style.css
fishpie/templates/delete.html
fishpie/templates/index.html
fishpie/templates/login.html
fishpie/translations/fr/LC_MESSAGES/messages.mo
FishPie-1.1.1.dist-info/COPYING
FishPie-1.1.1.dist-info/METADATA
FishPie-1.1.1.dist-info/WHEEL
FishPie-1.1.1.dist-info/top_level.txt
FishPie-1.1.1.dist-info/RECORD
