Metadata-Version: 2.1
Name: FishPie
Version: 1.1.1
Summary: File sharing web application
Home-page: https://github.com/lamyj/fishpie
Author: Julien Lamy
Author-email: julien@seasofcheese.net
License: GPL-3.0-or-later
Keywords: File sharing,Web application,Flask
Classifier: Development Status :: 5 - Production/Stable
Classifier: Environment :: Web Environment
Classifier: Framework :: Flask
Classifier: Intended Audience :: Information Technology
Classifier: Intended Audience :: System Administrators
Classifier: License :: OSI Approved :: GNU General Public License v3 or later (GPLv3+)
Classifier: Programming Language :: Python :: 3
Classifier: Topic :: Internet :: WWW/HTTP
License-File: COPYING
Requires-Dist: flask
Requires-Dist: flask-babel
Provides-Extra: wordpress-auth
Requires-Dist: mysqlclient ; extra == 'wordpress-auth'
